yabtc/__init__.py
yabtc/base58.py
yabtc/bech32.py
yabtc/config.py
yabtc/core.py
yabtc/denomination.py
yabtc/ecdsa.py
yabtc/opcode.py
yabtc/ripemd160.py
yabtc/rpc.py
yabtc/schnorr.py
yabtc/secp256k1.py
yabtc/wallet.py
yabtc-1.2.0.dist-info/METADATA
yabtc-1.2.0.dist-info/WHEEL
yabtc-1.2.0.dist-info/licenses/LICENSE
yabtc-1.2.0.dist-info/RECORD
