Metadata-Version: 2.3
Name: yabtc
Version: 1.2.0
Summary: Yabtc: bitcoin library for humans
Project-URL: homepage, https://github.com/mohanson/yabtc
Author-email: Mohanson <mohanson@outlook.com>
License: MIT License
Requires-Dist: requests
